{
  "id": "mlhw-final-polish",
  "name": "mlhw-final-polish",
  "title": "完善作业最终提交质量",
  "description": "补齐最终提交前的复现说明、自动自检脚本、README 导航和 PDF/清单证据。",
  "status": "completed",
  "dev_type": null,
  "scope": null,
  "package": null,
  "priority": "P2",
  "creator": "lf",
  "assignee": "lf",
  "createdAt": "2026-06-17",
  "completedAt": "2026-06-17",
  "branch": null,
  "base_branch": "main",
  "worktree_path": null,
  "commit": null,
  "pr_url": null,
  "subtasks": [],
  "children": [],
  "parent": null,
  "relatedFiles": [],
  "notes": "",
  "meta": {}
}
